youtube_wpm/__init__.py
youtube_wpm/__main__.py
youtube_wpm/__version__.py
youtube_wpm/_const.py
youtube_wpm/_logger.py
youtube_wpm/_youtube.py
youtube_wpm-0.1.0.dist-info/LICENSE
youtube_wpm-0.1.0.dist-info/METADATA
youtube_wpm-0.1.0.dist-info/WHEEL
youtube_wpm-0.1.0.dist-info/entry_points.txt
youtube_wpm-0.1.0.dist-info/top_level.txt
youtube_wpm-0.1.0.dist-info/RECORD
