Metadata-Version: 2.1
Name: youtube-wpm
Version: 0.1.0
Summary: youtube-wpm is a CLI tool to get a YouTube video's words per minute (WPM).
Home-page: https://github.com/thombashi/youtube-wpm
Author: Tsuyoshi Hombashi
Author-email: tsuyoshi.hombashi@gmail.com
License: MIT License
Project-URL: Changlog, https://github.com/thombashi/youtube-wpm/releases
Project-URL: Source, https://github.com/thombashi/youtube-wpm
Project-URL: Tracker, https://github.com/thombashi/youtube-wpm/issues
Keywords: YouTube,Transcript,WPM
Classifier: Development Status :: 3 - Alpha
Classifier: Environment :: Console
Classifier: Intended Audience :: Education
Classifier: License :: OSI Approved :: MIT License
Classifier: Operating System :: OS Independent
Classifier: Programming Language :: Python :: 3
Classifier: Programming Language :: Python :: 3.8
Classifier: Programming Language :: Python :: 3.9
Classifier: Programming Language :: Python :: 3.10
Classifier: Programming Language :: Python :: 3.11
Classifier: Programming Language :: Python :: 3.12
Classifier: Programming Language :: Python :: 3 :: Only
Classifier: Topic :: Terminals
Requires-Python: >=3.8
License-File: LICENSE
Requires-Dist: humanreadable <1,>=0.3
Requires-Dist: loguru <1,>=0.4.1
Requires-Dist: pytablewriter <2,>=1.2
Requires-Dist: pytube <16,>=11
Requires-Dist: youtube-transcript-api <1,>=0.5
Provides-Extra: test
Requires-Dist: pytest >=6.0.1 ; extra == 'test'
Requires-Dist: pytest-md-report >=0.5 ; extra == 'test'
